lensesio/__init__.py
lensesio/lenses.py
lensesio/core/__init__.py
lensesio/core/admin.py
lensesio/core/basic_auth.py
lensesio/core/endpoints.py
lensesio/core/exception.py
lensesio/core/exec_action.py
lensesio/core/krb_auth.py
lensesio/data/__init__.py
lensesio/data/connectors.py
lensesio/data/consumers.py
lensesio/data/data_subscribe.py
lensesio/data/policy.py
lensesio/data/processors.py
lensesio/data/sql.py
lensesio/data/topology.py
lensesio/flows/__init__.py
lensesio/flows/flows.py
lensesio/kafka/__init__.py
lensesio/kafka/acls.py
lensesio/kafka/quotas.py
lensesio/kafka/topics.py
lensesio/pulsar/__init__.py
lensesio/pulsar/pulsar_client.py
lensesio/registry/__init__.py
lensesio/registry/schemas.py
lensesio-4.0.1.dist-info/LICENSE.txt
lensesio-4.0.1.dist-info/METADATA
lensesio-4.0.1.dist-info/WHEEL
lensesio-4.0.1.dist-info/top_level.txt
lensesio-4.0.1.dist-info/RECORD
